detecthttp/__init__.py
detecthttp/_version.py
detecthttp/plugin.py
detecthttp/pytest.py
nose_detecthttp-1.2.1.dist-info/LICENSE
nose_detecthttp-1.2.1.dist-info/METADATA
nose_detecthttp-1.2.1.dist-info/WHEEL
nose_detecthttp-1.2.1.dist-info/entry_points.txt
nose_detecthttp-1.2.1.dist-info/top_level.txt
nose_detecthttp-1.2.1.dist-info/RECORD
