Metadata-Version: 2.1
Name: nose-detecthttp
Version: 1.2.1
Summary: A nose plugin to detect tests making http calls.
Home-page: https://github.com/venmo/nose-detecthttp
Author: Simon Weber
Author-email: simon@venmo.com
License: MIT
Platform: UNKNOWN
Classifier: Development Status :: 5 - Production/Stable
Classifier: Intended Audience :: Developers
Classifier: License :: OSI Approved :: MIT License
Classifier: Programming Language :: Python
Classifier: Programming Language :: Python :: 2
Classifier: Programming Language :: Python :: 2.7
Classifier: Programming Language :: Python :: 3
Classifier: Programming Language :: Python :: 3.5
Classifier: Programming Language :: Python :: 3.6
Classifier: Programming Language :: Python :: 3.7
Requires-Python: >=2.7, !=3.0.*, !=3.1.*, !=3.2.*, !=3.3.*, !=3.4.*
License-File: LICENSE
Requires-Dist: vcrpy (>=1.1.0)
